{
  "type": "FeatureCollection",
  "features": [
    {
      "type": "Feature",
      "properties": {
        "description": "Spadina streetcar line",
        "color": "red",
        "rank": "7",
        "ascii": "71"
      },
      "geometry": {
        "type": "LineString",
        "coordinates": [
          [
            -79.403832,
            43.667354
          ],
          [
            -79.391923,
            43.638630
          ]
        ]
      }
    },
    {
      "type": "Feature",
      "properties": {
        "description": "Bathurst station",
        "color": "blue",
        "rank": "7",
        "ascii": "71"
      },
      "geometry": {
        "type": "Point",
        "coordinates": [
          -79.411111,
          43.666111
        ]
      }
    },
    {
      "type": "Feature",
      "properties": {
        "description": "Bloor-Yonge station",
        "color": "blue",
        "rank": "7",
        "ascii": "71"
      },
      "geometry": {
        "type": "Point",
        "coordinates": [-79.385971, 43.670900]
      }
    },
    {
      "type": "Feature",
      "properties": {
        "description": "Broadview station",
        "color": "blue",
        "rank": "7",
        "ascii": "71"
      },
      "geometry": {
        "type": "Point",
        "coordinates": [-79.358233, 43.676974]
      }
    },
    {
      "type": "Feature",
      "properties": {
        "description": "College station",
        "color": "blue",
        "rank": "7",
        "ascii": "71"
      },
      "geometry": {
        "type": "Point",
        "coordinates": [-79.383103, 43.660801]
      }
    },
    {
      "type": "Feature",
      "properties": {
        "description": "Davisville station",
        "color": "blue",
        "rank": "7",
        "ascii": "71"
      },
      "geometry": {
        "type": "Point",
        "coordinates": [-79.397480,43.697140]
      }
    },
    {
      "type": "Feature",
      "properties": {
        "description": "Don Mills station",
        "color": "blue",
        "rank": "7",
        "ascii": "71"
      },
      "geometry": {
        "type": "Point",
        "coordinates": [-79.345880, 43.776117]
      }
    },
    {
      "type": "Feature",
      "properties": {
        "description": "Downsview station",
        "color": "blue",
        "rank": "7",
        "ascii": "71"
      },
      "geometry": {
        "type": "Point",
        "coordinates": [-79.462206, 43.749120]
      }
    },
    {
      "type": "Feature",
      "properties": {
        "description": "Dundas station",
        "color": "blue",
        "rank": "7",
        "ascii": "71"
      },
      "geometry": {
        "type": "Point",
        "coordinates": [-79.381283,43.656353]
      }
    },
    {
      "type": "Feature",
      "properties": {
        "description": "Dundas West station",
        "color": "blue",
        "rank": "7",
        "ascii": "71"
      },
      "geometry": {
        "type": "Point",
        "coordinates": [-79.453484,43.656770]
      }
    },
    {
      "type": "Feature",
      "properties": {
        "description": "Finch station",
        "color": "blue",
        "rank": "7",
        "ascii": "71"
      },
      "geometry": {
        "type": "Point",
        "coordinates": [-79.414625,43.780479]
      }
    },
    {
      "type": "Feature",
      "properties": {
        "description": "Islington station",
        "color": "blue",
        "rank": "7",
        "ascii": "71"
      },
      "geometry": {
        "type": "Point",
        "coordinates": [-79.523935,43.645279]
      }
    },
    {
      "type": "Feature",
      "properties": {
        "description": "King station",
        "color": "blue",
        "rank": "7",
        "ascii": "71"
      },
      "geometry": {
        "type": "Point",
        "coordinates": [-79.377925,43.649172]
      }
    },
        {
      "type": "Feature",
      "properties": {
        "description": "Kipling station",
        "color": "blue",
        "rank": "7",
        "ascii": "71"
      },
      "geometry": {
        "type": "Point",
        "coordinates": [-79.536111, 43.637222]
      }
    },
    {
      "type": "Feature",
      "properties": {
        "description": "Museum station",
        "color": "blue",
        "rank": "7",
        "ascii": "71"
      },
      "geometry": {
        "type": "Point",
        "coordinates": [-79.393594,43.667030]
      }
    },
    {
      "type": "Feature",
      "properties": {
        "description": "Osgoode station",
        "color": "blue",
        "rank": "7",
        "ascii": "71"
      },
      "geometry": {
        "type": "Point",
        "coordinates": [-79.386971,43.651007]
      }
    },
    {
      "type": "Feature",
      "properties": {
        "description": "Queen station",
        "color": "blue",
        "rank": "7",
        "ascii": "71"
      },
      "geometry": {
        "type": "Point",
        "coordinates": [-79.379648,43.652959]
      }
    },
    {
      "type": "Feature",
      "properties": {
        "description": "Queen’s Park station",
        "color": "blue",
        "rank": "7",
        "ascii": "71"
      },
      "geometry": {
        "type": "Point",
        "coordinates": [-79.390043,43.660090]
      }
    },
    {
      "type": "Feature",
      "properties": {
        "description": "Scarborough Centre station",
        "color": "blue",
        "rank": "7",
        "ascii": "71"
      },
      "geometry": {
        "type": "Point",
        "coordinates": [-79.257756,43.774401]
      }
    },
    {
      "type": "Feature",
      "properties": {
        "description": "Sheppard-Yonge station",
        "color": "blue",
        "rank": "7",
        "ascii": "71"
      },
      "geometry": {
        "type": "Point",
        "coordinates": [-79.412075,43.761583]
      }
    },
    {
      "type": "Feature",
      "properties": {
        "description": "Spadina station",
        "color": "blue",
        "rank": "7",
        "ascii": "71"
      },
      "geometry": {
        "type": "Point",
        "coordinates": [
          -79.403832,
          43.667354
        ]
      }
    },
    {
      "type": "Feature",
      "properties": {
        "description": "St Andrew station",
        "color": "blue",
        "rank": "7",
        "ascii": "71"
      },
      "geometry": {
        "type": "Point",
        "coordinates": [-79.385056,43.647545]
      }
    },
    {
      "type": "Feature",
      "properties": {
        "description": "St George station",
        "color": "blue",
        "rank": "7",
        "ascii": "71"
      },
      "geometry": {
        "type": "Point",
        "coordinates": [-79.397910,43.668706]
      }
    },
    {
      "type": "Feature",
      "properties": {
        "description": "St Patrick station",
        "color": "blue",
        "rank": "7",
        "ascii": "71"
      },
      "geometry": {
        "type": "Point",
        "coordinates": [-79.388661,43.654987]
      }
    },
    {
      "type": "Feature",
      "properties": {
        "description": "Union station",
        "color": "blue",
        "rank": "7",
        "ascii": "71"
      },
      "geometry": {
        "type": "Point",
        "coordinates": [-79.380989,43.645256]
      }
    },
    {
      "type": "Feature",
      "properties": {
        "description": "Yorkdale station",
        "color": "blue",
        "rank": "7",
        "ascii": "71"
      },
      "geometry": {
        "type": "Point",
        "coordinates": [-79.447507,43.724545]
      }
    },
    {
      "type": "Feature",
      "properties": {
        "description": "York Mills station",
        "color": "blue",
        "rank": "7",
        "ascii": "71"
      },
      "geometry": {
        "type": "Point",
        "coordinates": [-79.406427,43.744853]
      }
    }
  ]
}
